{
  "name": "hanazuki-nftables",
  "version": "0.1.0",
  "author": "hanazuki",
  "summary": "Configure nftables ruleset",
  "license": "MIT",
  "source": "https://github.com/hanazuki/puppet-nftables",
  "project_page": "https://github.com/hanazuki/puppet-nftables",
  "issues_url": "https://github.com/hanazuki/puppet-nftables/issues",
  "tags": ["nftables", "firewall"],
  "dependencies": [
    {"name": "puppetlabs/stdlib", "version_requirement": ">= 4.0.0 < 5.0.0"},
    {"name": "puppetlabs/concat", "version_requirement": ">= 4.0.0"}
  ],
  "operatingsystem_support": [
    {"operatingsystem": "Debian", "operatingsystemrelease": ["9"]}
  ]
}
